LICENSE.txt
README.md
setup.cfg
setup.py
fscloudutils/DB_client.py
fscloudutils/chatbot.py
fscloudutils/data_validation.py
fscloudutils/exceptions.py
fscloudutils/processors.py
fscloudutils/utils.py
fscloudutils.egg-info/PKG-INFO
fscloudutils.egg-info/SOURCES.txt
fscloudutils.egg-info/dependency_links.txt
fscloudutils.egg-info/requires.txt
fscloudutils.egg-info/top_level.txt