Metadata-Version: 2.1
Name: fscloudutils
Version: 1.0.40
Summary: A package for all fs cloud utilities
Author: Yotam Raz, Maayan Shriki
License: MIT
Requires-Python: >=3.6
License-File: LICENSE.txt
